uipath_llama/__init__.py
uipath_llama/middlewares.py
uipath_llama/_cli/__init__.py
uipath_llama/_cli/cli_init.py
uipath_llama/_cli/cli_run.py
uipath_llama/_cli/_runtime/_context.py
uipath_llama/_cli/_runtime/_exception.py
uipath_llama/_cli/_runtime/_runtime.py
uipath_llama/_cli/_utils/_config.py
uipath_llama-0.0.1.dist-info/METADATA
uipath_llama-0.0.1.dist-info/WHEEL
uipath_llama-0.0.1.dist-info/entry_points.txt
uipath_llama-0.0.1.dist-info/licenses/LICENSE
uipath_llama-0.0.1.dist-info/RECORD
