Metadata-Version: 2.4
Name: uipath-llama
Version: 0.0.1
Summary: UiPath Llama SDK
Project-URL: Homepage, https://uipath.com
Project-URL: Repository, https://github.com/UiPath/uipath-llama-python
Maintainer-email: Marius Cosareanu <marius.cosareanu@uipath.com>, Cristian Pufu <cristian.pufu@uipath.com>
License-File: LICENSE
Classifier: Development Status :: 3 - Alpha
Classifier: Intended Audience :: Developers
Classifier: Programming Language :: Python :: 3.10
Classifier: Programming Language :: Python :: 3.11
Classifier: Programming Language :: Python :: 3.12
Classifier: Topic :: Software Development :: Build Tools
Requires-Python: >=3.10
Requires-Dist: uipath>=2.0.56
